{
  "ranking_type": "monthly",
  "generated_at": "2026-05-01T04:13:03.590693+09:00",
  "period_start": "2026-05-01T00:00:00+09:00",
  "period_end": "2026-05-01T03:34:49+09:00",
  "items": [
    {
      "like_user_id": "12848229",
      "creator_name": "そら",
      "creator_urlname": "flux_water",
      "creator_url": "https://note.com/flux_water",
      "has_profile_url": true,
      "likes_count": 5,
      "first_like_at": "2026-05-01T00:13:35+09:00",
      "last_like_at": "2026-05-01T00:37:33+09:00",
      "follower_count": 87,
      "ranking_type": "monthly",
      "generated_at": "2026-05-01T04:13:03.590693+09:00",
      "period_start": "2026-05-01T00:00:00+09:00",
      "period_end": "2026-05-01T03:34:49+09:00",
      "rank": 1
    },
    {
      "like_user_id": "13342222",
      "creator_name": "青空 和平",
      "creator_urlname": "brisk_viola3314",
      "creator_url": "https://note.com/brisk_viola3314",
      "has_profile_url": true,
      "likes_count": 4,
      "first_like_at": "2026-05-01T02:40:19+09:00",
      "last_like_at": "2026-05-01T02:48:13+09:00",
      "follower_count": 653,
      "ranking_type": "monthly",
      "generated_at": "2026-05-01T04:13:03.590693+09:00",
      "period_start": "2026-05-01T00:00:00+09:00",
      "period_end": "2026-05-01T03:34:49+09:00",
      "rank": 2
    },
    {
      "like_user_id": "2888910",
      "creator_name": "氷河期世代おじさん代表",
      "creator_urlname": "hyougakioji",
      "creator_url": "https://note.com/hyougakioji",
      "has_profile_url": true,
      "likes_count": 2,
      "first_like_at": "2026-05-01T01:02:02+09:00",
      "last_like_at": "2026-05-01T01:02:06+09:00",
      "follower_count": 644,
      "ranking_type": "monthly",
      "generated_at": "2026-05-01T04:13:03.590693+09:00",
      "period_start": "2026-05-01T00:00:00+09:00",
      "period_end": "2026-05-01T03:34:49+09:00",
      "rank": 3
    },
    {
      "like_user_id": "11630336",
      "creator_name": "AIUU",
      "creator_urlname": "realme_note",
      "creator_url": "https://note.com/realme_note",
      "has_profile_url": true,
      "likes_count": 1,
      "first_like_at": "2026-05-01T00:40:37+09:00",
      "last_like_at": "2026-05-01T00:40:37+09:00",
      "follower_count": 1052,
      "ranking_type": "monthly",
      "generated_at": "2026-05-01T04:13:03.590693+09:00",
      "period_start": "2026-05-01T00:00:00+09:00",
      "period_end": "2026-05-01T03:34:49+09:00",
      "rank": 4
    },
    {
      "like_user_id": "14367265",
      "creator_name": "ハートK",
      "creator_urlname": "limber_egret3827",
      "creator_url": "https://note.com/limber_egret3827",
      "has_profile_url": true,
      "likes_count": 1,
      "first_like_at": "2026-05-01T00:32:40+09:00",
      "last_like_at": "2026-05-01T00:32:40+09:00",
      "follower_count": 10,
      "ranking_type": "monthly",
      "generated_at": "2026-05-01T04:13:03.590693+09:00",
      "period_start": "2026-05-01T00:00:00+09:00",
      "period_end": "2026-05-01T03:34:49+09:00",
      "rank": 5
    }
  ]
}